cccv/__init__.py
cccv/arch/__init__.py
cccv/arch/arch_util.py
cccv/arch/auxnet/__init__.py
cccv/arch/auxnet/spynet_arch.py
cccv/arch/sr/__init__.py
cccv/arch/sr/dat_arch.py
cccv/arch/sr/edsr_arch.py
cccv/arch/sr/hat_arch.py
cccv/arch/sr/rrdb_arch.py
cccv/arch/sr/scunet_arch.py
cccv/arch/sr/srcnn_arch.py
cccv/arch/sr/srvgg_arch.py
cccv/arch/sr/swinir_arch.py
cccv/arch/sr/upcunet_arch.py
cccv/arch/vfi/__init__.py
cccv/arch/vfi/drba_arch.py
cccv/arch/vfi/ifnet_arch.py
cccv/arch/vfi/vfi_utils/__init__.py
cccv/arch/vfi/vfi_utils/softsplat.py
cccv/arch/vfi/vfi_utils/softsplat_torch.py
cccv/arch/vfi/vfi_utils/warplayer.py
cccv/arch/vsr/__init__.py
cccv/arch/vsr/edvr_arch.py
cccv/arch/vsr/msrswvsr_arch.py
cccv/auto/__init__.py
cccv/auto/config.py
cccv/auto/model.py
cccv/config/__init__.py
cccv/config/base_config.py
cccv/config/auxnet/__init__.py
cccv/config/auxnet/spynet_config.py
cccv/config/sr/__init__.py
cccv/config/sr/dat_config.py
cccv/config/sr/edsr_config.py
cccv/config/sr/hat_config.py
cccv/config/sr/realcugan_config.py
cccv/config/sr/realesrgan_config.py
cccv/config/sr/scunet_config.py
cccv/config/sr/srcnn_config.py
cccv/config/sr/swinir_config.py
cccv/config/vfi/drba_config.py
cccv/config/vfi/rife_config.py
cccv/config/vsr/__init__.py
cccv/config/vsr/animesr_config.py
cccv/config/vsr/edvr_config.py
cccv/model/__init__.py
cccv/model/auxiliary_base_model.py
cccv/model/base_model.py
cccv/model/sr_base_model.py
cccv/model/tile.py
cccv/model/vfi_base_model.py
cccv/model/vsr_base_model.py
cccv/model/auxnet/__init__.py
cccv/model/auxnet/spynet_model.py
cccv/model/sr/__init__.py
cccv/model/sr/realcugan_model.py
cccv/model/vfi/__init__.py
cccv/model/vfi/drba_model.py
cccv/model/vfi/rife_model.py
cccv/model/vsr/__init__.py
cccv/model/vsr/edvr_model.py
cccv/type/__init__.py
cccv/type/arch.py
cccv/type/base.py
cccv/type/config.py
cccv/type/model.py
cccv/util/__init__.py
cccv/util/color.py
cccv/util/device.py
cccv/util/misc.py
cccv/util/registry.py
cccv/util/remote.py
cccv-0.0.4.dist-info/METADATA
cccv-0.0.4.dist-info/WHEEL
cccv-0.0.4.dist-info/licenses/LICENSE
cccv-0.0.4.dist-info/RECORD
