Metadata-Version: 2.4
Name: cccv
Version: 0.0.4
Summary: an inference lib for image/video restoration and video frame interpolation with VapourSynth support
Project-URL: Homepage, https://github.com/EutropicAI/cccv
Project-URL: Repository, https://github.com/EutropicAI/cccv
Author: Tohrusky
License-Expression: MIT
License-File: LICENSE
Classifier: Programming Language :: Python :: 3.9
Classifier: Programming Language :: Python :: 3.10
Classifier: Programming Language :: Python :: 3.11
Classifier: Programming Language :: Python :: 3.12
Classifier: Programming Language :: Python :: 3.13
Requires-Python: <4,>=3.9
Requires-Dist: einops
Requires-Dist: opencv-python
Requires-Dist: pydantic
Requires-Dist: tenacity
